termcolorlog/__init__.py
termcolorlog/termcolorlog.py
termcolorlog-0.1.0.dist-info/METADATA
termcolorlog-0.1.0.dist-info/WHEEL
termcolorlog-0.1.0.dist-info/top_level.txt
termcolorlog-0.1.0.dist-info/RECORD
